Workbook

Sheet Read Me
A1: ABC CORPORATION | FINANCIAL ANALYSIS
A3: Project | B3: Financial Analysis and Presentation
A4: Purpose | B4: Analyze illustrative financial statements for 2023–2025 using Excel formulas, ratios, and charts.
A5: Units | B5: All financial statement amounts are in USD thousands unless stated otherwise.
A6: Important note | B6: All company figures are fictional sample data created for an educational project.
A7: How to use | B7: Review Income Statement, Balance Sheet, Cash Flow, Ratios, and Trend Analysis worksheets.
A8: Prepared for | B8: DS Lab using Excel Mini Project

Sheet Income Statement
A1: INCOME STATEMENT
A2: USD thousands (illustrative sample data)
A4: Line Item | B4: 2023 | C4: 2024 | D4: 2025
A5: Revenue | B5: 1200 | C5: 1380 | D5: 1560
A6: Cost of Goods Sold | B6: 720 | C6: 814 | D6: 905
A7: Gross Profit | B7: 480 | C7: 566 | D7: 655
A8: Operating Expenses | B8: 300 | C8: 330 | D8: 365
A9: Operating Income | B9: 180 | C9: 236 | D9: 290
A10: Interest Expense | B10: 24 | C10: 26 | D10: 28
A11: Income Before Tax | B11: 156 | C11: 210 | D11: 262
A12: Tax Expense | B12: 39 | C12: 53 | D12: 66
A13: Net Income | B13: 117 | C13: 157 | D13: 196

Sheet Balance Sheet
A1: BALANCE SHEET
A2: USD thousands (illustrative sample data)
A4: Line Item | B4: 2023 | C4: 2024 | D4: 2025
A5: Cash and Cash Equivalents | B5: 150 | C5: 205 | D5: 268
A6: Accounts Receivable | B6: 180 | C6: 205 | D6: 230
A7: Inventory | B7: 140 | C7: 155 | D7: 170
A8: Total Current Assets | B8: 470 | C8: 565 | D8: 668
A9: Property, Plant & Equipment | B9: 500 | C9: 530 | D9: 560
A10: Total Assets | B10: 970 | C10: 1095 | D10: 1228
A11: Accounts Payable | B11: 130 | C11: 145 | D11: 155
A12: Short-term Debt | B12: 70 | C12: 65 | D12: 60
A13: Total Current Liabilities | B13: 200 | C13: 210 | D13: 215
A14: Long-term Debt | B14: 260 | C14: 245 | D14: 225
A15: Total Liabilities | B15: 460 | C15: 455 | D15: 440
... A17: Total Liabilities & Equity | B17: 970 | C17: 1095 | D17: 1228

Sheet Cash Flow
A1: CASH FLOW STATEMENT
A2: USD thousands (illustrative sample data)
A4: Line Item | B4: 2023 | C4: 2024 | D4: 2025
A5: Net Income | B5: 117 | C5: 157 | D5: 196
A6: Depreciation & Amortization | B6: 45 | C6: 48 | D6: 52
A7: Change in Working Capital | B7: -20 | C7: -18 | D7: -15
A8: Net Cash from Operating Activities | B8: 142 | C8: 187 | D8: 233
A9: Capital Expenditures | B9: -75 | C9: -82 | D9: -90
A10: Net Cash from Investing Activities | B10: -75 | C10: -82 | D10: -90
A11: Debt Issued / (Repaid) | B11: -20 | C11: -20 | D11: -25
A12: Dividends Paid | B12: -25 | C12: -30 | D12: -35
A13: Net Cash from Financing Activities | B13: -45 | C13: -50 | D13: -60
A14: Net Change in Cash | B14: 22 | C14: 55 | D14: 63
A15: Beginning Cash | B15: 128 | C15: 150 | D15: 205
A16: Ending Cash | B16: 150 | C16: 205 | D16: 268

Sheet Ratios
A1: FINANCIAL RATIOS
A2: Formula-driven calculations linked to the financial statement worksheets.
A4: Ratio | B4: 2023 | C4: 2024 | D4: 2025
A5: Current Ratio | B5: ='Balance Sheet'!B8/'Balance Sheet'!B13 | C5: ='Balance Sheet'!C8/'Balance Sheet'!C13 | D5: ='Balance Sheet'!D8/'Balance Sheet'!D13
A6: Quick Ratio | B6: =('Balance Sheet'!B8-'Balance Sheet'!B7)/'Balance Sheet'!B13 | C6: =('Balance Sheet'!C8-'Balance Sheet'!C7)/'Balance Sheet'!C13 | D6: =('Balance Sheet'!D8-'Balance Sheet'!D7)/'Balance Sheet'!D13
A7: Gross Profit Margin | B7: ='Income Statement'!B7/'Income Statement'!B5 | C7: ='Income Statement'!C7/'Income Statement'!C5 | D7: ='Income Statement'!D7/'Income Statement'!D5
A8: Operating Profit Margin | B8: ='Income Statement'!B9/'Income Statement'!B5 | C8: ='Income Statement'!C9/'Income Statement'!C5 | D8: ='Income Statement'!D9/'Income Statement'!D5
A9: Net Profit Margin | B9: ='Income Statement'!B13/'Income Statement'!B5 | C9: ='Income Statement'!C13/'Income Statement'!C5 | D9: ='Income Statement'!D13/'Income Statement'!D5
A10: Debt-to-Assets | B10: ='Balance Sheet'!B15/'Balance Sheet'!B10 | C10: ='Balance Sheet'!C15/'Balance Sheet'!C10 | D10: ='Balance Sheet'!D15/'Balance Sheet'!D10
A11: Debt-to-Equity | B11: ='Balance Sheet'!B15/'Balance Sheet'!B16 | C11: ='Balance Sheet'!C15/'Balance Sheet'!C16 | D11: ='Balance Sheet'!D15/'Balance Sheet'!D16
A12: Return on Assets | B12: ='Income Statement'!B13/'Balance Sheet'!B10 | C12: ='Income Statement'!C13/'Balance Sheet'!C10 | D12: ='Income Statement'!D13/'Balance Sheet'!D10
A13: Return on Equity | B13: ='Income Statement'!B13/'Balance Sheet'!B16 | C13: ='Income Statement'!C13/'Balance Sheet'!C16 | D13: ='Income Statement'!D13/'Balance Sheet'!D16

Sheet Trend Analysis
A1: TREND ANALYSIS
A3: Metric | B3: 2023 | C3: 2024 | D3: 2025
A4: Revenue | B4: ='Income Statement'!B5 | C4: ='Income Statement'!C5 | D4: ='Income Statement'!D5
A5: Gross Profit | B5: ='Income Statement'!B7 | C5: ='Income Statement'!C7 | D5: ='Income Statement'!D7
A6: Operating Income | B6: ='Income Statement'!B9 | C6: ='Income Statement'!C9 | D6: ='Income Statement'!D9
A7: Net Income | B7: ='Income Statement'!B13 | C7: ='Income Statement'!C13 | D7: ='Income Statement'!D13
A8: Total Assets | B8: ='Balance Sheet'!B10 | C8: ='Balance Sheet'!C10 | D8: ='Balance Sheet'!D10
A9: Ending Cash | B9: ='Cash Flow'!B16 | C9: ='Cash Flow'!C16 | D9: ='Cash Flow'!D16
A12: Year-over-year growth
A13: Metric | B13: 2024 vs 2023 | C13: 2025 vs 2024
A14: Revenue | B14: =C4/B4-1 | C14: =D4/C4-1
A15: Gross Profit | B15: =C5/B5-1 | C15: =D5/C5-1
A16: Operating Income | B16: =C6/B6-1 | C16: =D6/C6-1
A17: Net Income | B17: =C7/B7-1 | C17: =D7/C7-1
A18: Total Assets | B18: =C8/B8-1 | C18: =D8/C8-1
A19: Ending Cash | B19: =C9/B9-1 | C19: =D9/C9-1
